pyplAI/Algoritmos.py
pyplAI/__init__.py
pyplAI-1.0.3.dist-info/LICENSE.md
pyplAI-1.0.3.dist-info/METADATA
pyplAI-1.0.3.dist-info/WHEEL
pyplAI-1.0.3.dist-info/top_level.txt
pyplAI-1.0.3.dist-info/RECORD
