Metadata-Version: 2.1
Name: pyplAI
Version: 1.0.3
Summary: Biblioteca para Python con algoritmos de resolución de juegos de mesa (minimax, MCTS, SO-ISMCTS y MO-ISMCTS)
Home-page: https://github.com/plss12/pyplAI
Author: Pedro Luis Soto Santos
Author-email: pepoluis712@gmail.com
License: MIT
Keywords: python,articial intelligence,AI,games,board games,minimax,alpha-beta,monte carlo,monte carlo tree search,UCT,game theory,information set,perfect information,imperfect information
Classifier: Development Status :: 4 - Beta
Classifier: Intended Audience :: Developers
Classifier: Intended Audience :: Science/Research
Classifier: Intended Audience :: Education
Classifier: License :: OSI Approved :: MIT License
Classifier: Natural Language :: Spanish
Classifier: Natural Language :: English
Classifier: Operating System :: OS Independent
Classifier: Programming Language :: Python :: 3
Classifier: Topic :: Games/Entertainment :: Board Games
Classifier: Topic :: Scientific/Engineering :: Artificial Intelligence
Classifier: Topic :: Software Development :: Libraries :: Python Modules
Classifier: Typing :: Typed
License-File: LICENSE.md
